cassandra_step/__init__.py
cassandra_step/cassandra.py
cassandra_step/cassandra_parameters.py
cassandra_step/cassandra_step.py
cassandra_step/tk_cassandra.py
cassandra_step-0.2.1.dist-info/DESCRIPTION.rst
cassandra_step-0.2.1.dist-info/METADATA
cassandra_step-0.2.1.dist-info/RECORD
cassandra_step-0.2.1.dist-info/WHEEL
cassandra_step-0.2.1.dist-info/entry_points.txt
cassandra_step-0.2.1.dist-info/metadata.json
cassandra_step-0.2.1.dist-info/top_level.txt
