Metadata-Version: 2.0
Name: cassandra-step
Version: 0.2.1
Summary: Cassandra is a Monte Carlo molecular simulation package.
Home-page: https://github.com/emarinri/cassandra_step
Author: Eliseo Marin-Rimoldi
Author-email: meliseo@vt.edu
License: BSD license
Keywords: cassandra_step
Platform: UNKNOWN
Classifier: Development Status :: 2 - Pre-Alpha
Classifier: Intended Audience :: Science/Research
Classifier: Topic :: Scientific/Engineering :: Chemistry
Classifier: Topic :: Scientific/Engineering :: Physics
Classifier: License :: OSI Approved :: BSD License
Classifier: Natural Language :: English
Classifier: Programming Language :: Python :: 3 :: Only
Classifier: Programming Language :: Python :: 3.5
Classifier: Programming Language :: Python :: 3.6
Classifier: Programming Language :: Python :: 3.7
Requires-Dist: Pmw
Requires-Dist: pprint
Requires-Dist: seamm (>=0.1)
Requires-Dist: seamm-util (>=0.1)
Requires-Dist: seamm-widgets
